CHANGELOG.md
limu.py
limu_original.py
limu-0.0.38.dist-info/entry_points.txt
limu-0.0.38.dist-info/WHEEL
limu-0.0.38.dist-info/METADATA
limu-0.0.38.dist-info/RECORD
