Metadata-Version: 2.1
Name: limu
Version: 0.0.38
Summary: Tool to analyse images of cleared and trypan blue stained leaves to assess leaf damage.
License: GPL-3.0-or-later
Author: Tobias U. T. Lindblom
Maintainer: Tobias U. T. Lindblom
Maintainer-email: tobias.lindblom@gmail.com
Requires-Python: >=3.9,<3.12
Classifier: License :: OSI Approved :: GNU General Public License v3 or later (GPLv3+)
Classifier: Programming Language :: Python :: 3
Classifier: Programming Language :: Python :: 3.9
Classifier: Programming Language :: Python :: 3.10
Requires-Dist: hdbscan (>=0.8,<0.9)
Requires-Dist: numpy (>=1.23,<2.0)
Requires-Dist: pandas (>=1.1,<2.0)
Requires-Dist: rawpy (>=0.17,<0.18)
Requires-Dist: scikit-image (>=0.19,<0.20)
Requires-Dist: scikit-learn (>=1.0,<2.0)
Requires-Dist: scipy (>=1.9,<2.0)
